<?xml version="1.0" encoding="utf-8"?>
<!DOCTYPE hibernate-mapping PUBLIC "-//Hibernate/Hibernate Mapping DTD 3.0//EN"
"http://hibernate.sourceforge.net/hibernate-mapping-3.0.dtd">
<!-- 
    Mapping file autogenerated by MyEclipse Persistence Tools
-->
<hibernate-mapping>
    <class name="org.ski.dvx.server.hibernate.country.Country" table="country" catalog="sk_dvx_long">
        <id name="countryId" type="java.lang.Integer">
            <column name="country_id" />
            <generator class="native" />
        </id>
        <property name="countryName" type="java.lang.String">
            <column name="country_name" length="65535" />
        </property>
        <property name="countryNameShort" type="java.lang.String">
            <column name="country_name_short" length="65535" />
        </property>
        <property name="continentIdFk" type="java.lang.Integer">
            <column name="continent_id_fk" />
        </property>
        <property name="modified" type="java.lang.Long">
            <column name="modified" />
        </property>
        <property name="created" type="java.lang.Long">
            <column name="created" />
        </property>
    </class>
</hibernate-mapping>
